[
  {
    "id": 4,
    "name": "SYS-001: Maximum Takeoff Weight",
    "description": "The drone shall have a maximum takeoff weight not exceeding 25 kg",
    "uri": null,
    "properties": {
      "status": "active",
      "priority": "critical",
      "threshold": "25 kg",
      "source_document": "SRD v2.1",
      "verification_method": "test"
    },
    "objectStorageId": null,
    "originalId": "SYS-001",
    "classId": 10,
    "dataSourceId": 2,
    "projectId": 2,
    "organizationId": 1,
    "lastUpdatedAt": "2026-03-04T19:13:16.996011",
    "lastUpdatedBy": 1,
    "isArchived": false,
    "fileType": null,
    "tags": [
      {
        "id": 1,
        "name": "critical-path"
      }
    ],
    "labels": [],
    "class_name": "System Requirement"
  },
  {
    "id": 5,
    "name": "SYS-002: Operational Range",
    "description": "The drone shall achieve a minimum operational range of 50 km",
    "uri": null,
    "properties": {
      "status": "active",
      "priority": "critical",
      "threshold": "50 km",
      "source_document": "SRD v2.1",
      "verification_method": "demonstration"
    },
    "objectStorageId": null,
    "originalId": "SYS-002",
    "classId": 10,
    "dataSourceId": 2,
    "projectId": 2,
    "organizationId": 1,
    "lastUpdatedAt": "2026-03-04T19:13:16.996011",
    "lastUpdatedBy": 1,
    "isArchived": false,
    "fileType": null,
    "tags": [],
    "labels": [],
    "class_name": "System Requirement"
  },
  {
    "id": 6,
    "name": "SYS-003: Maximum Speed",
    "description": "The drone shall achieve a maximum airspeed of 120 km/h in level flight",
    "uri": null,
    "properties": {
      "status": "active",
      "priority": "high",
      "threshold": "120 km/h",
      "source_document": "SRD v2.1",
      "verification_method": "test"
    },
    "objectStorageId": null,
    "originalId": "SYS-003",
    "classId": 10,
    "dataSourceId": 2,
    "projectId": 2,
    "organizationId": 1,
    "lastUpdatedAt": "2026-03-04T19:13:16.996011",
    "lastUpdatedBy": 1,
    "isArchived": false,
    "fileType": null,
    "tags": [],
    "labels": [],
    "class_name": "System Requirement"
  },
  {
    "id": 7,
    "name": "SYS-004: Endurance",
    "description": "The drone shall sustain flight for a minimum of 90 minutes at cruise speed",
    "uri": null,
    "properties": {
      "status": "active",
      "priority": "critical",
      "threshold": "90 min",
      "source_document": "SRD v2.1",
      "verification_method": "test"
    },
    "objectStorageId": null,
    "originalId": "SYS-004",
    "classId": 10,
    "dataSourceId": 2,
    "projectId": 2,
    "organizationId": 1,
    "lastUpdatedAt": "2026-03-04T19:13:16.996011",
    "lastUpdatedBy": 1,
    "isArchived": false,
    "fileType": null,
    "tags": [
      {
        "id": 1,
        "name": "critical-path"
      }
    ],
    "labels": [],
    "class_name": "System Requirement"
  },
  {
    "id": 8,
    "name": "SYS-005: Operating Temperature",
    "description": "The drone shall operate in ambient temperatures from -20C to +50C",
    "uri": null,
    "properties": {
      "status": "active",
      "priority": "high",
      "range_max": "50 C",
      "range_min": "-20 C",
      "source_document": "SRD v2.1",
      "verification_method": "analysis"
    },
    "objectStorageId": null,
    "originalId": "SYS-005",
    "classId": 10,
    "dataSourceId": 2,
    "projectId": 2,
    "organizationId": 1,
    "lastUpdatedAt": "2026-03-04T19:13:16.996011",
    "lastUpdatedBy": 1,
    "isArchived": false,
    "fileType": null,
    "tags": [],
    "labels": [],
    "class_name": "System Requirement"
  },
  {
    "id": 9,
    "name": "SYS-006: Payload Capacity",
    "description": "The drone shall carry a minimum payload of 3 kg",
    "uri": null,
    "properties": {
      "status": "active",
      "priority": "high",
      "threshold": "3 kg",
      "source_document": "SRD v2.1",
      "verification_method": "test"
    },
    "objectStorageId": null,
    "originalId": "SYS-006",
    "classId": 10,
    "dataSourceId": 2,
    "projectId": 2,
    "organizationId": 1,
    "lastUpdatedAt": "2026-03-04T19:13:16.996011",
    "lastUpdatedBy": 1,
    "isArchived": false,
    "fileType": null,
    "tags": [],
    "labels": [],
    "class_name": "System Requirement"
  },
  {
    "id": 10,
    "name": "SYS-007: Wind Resistance",
    "description": "The drone shall maintain stable flight in winds up to 40 km/h",
    "uri": null,
    "properties": {
      "status": "active",
      "priority": "medium",
      "threshold": "40 km/h",
      "source_document": "SRD v2.1",
      "verification_method": "test"
    },
    "objectStorageId": null,
    "originalId": "SYS-007",
    "classId": 10,
    "dataSourceId": 2,
    "projectId": 2,
    "organizationId": 1,
    "lastUpdatedAt": "2026-03-04T19:13:16.996011",
    "lastUpdatedBy": 1,
    "isArchived": false,
    "fileType": null,
    "tags": [],
    "labels": [],
    "class_name": "System Requirement"
  },
  {
    "id": 11,
    "name": "SYS-008: Autonomous Navigation",
    "description": "The drone shall execute pre-programmed waypoint missions autonomously",
    "uri": null,
    "properties": {
      "status": "active",
      "priority": "critical",
      "source_document": "SRD v2.1",
      "verification_method": "demonstration"
    },
    "objectStorageId": null,
    "originalId": "SYS-008",
    "classId": 10,
    "dataSourceId": 2,
    "projectId": 2,
    "organizationId": 1,
    "lastUpdatedAt": "2026-03-04T19:13:16.996011",
    "lastUpdatedBy": 1,
    "isArchived": false,
    "fileType": null,
    "tags": [
      {
        "id": 1,
        "name": "critical-path"
      }
    ],
    "labels": [],
    "class_name": "System Requirement"
  },
  {
    "id": 12,
    "name": "PERF-001: Structural Load Factor",
    "description": "Airframe shall withstand 4g load factor with 1.5x safety margin",
    "uri": null,
    "properties": {
      "parent_req": "SYS-001",
      "load_factor": "4g",
      "safety_margin": 1.5
    },
    "objectStorageId": null,
    "originalId": "PERF-001",
    "classId": 11,
    "dataSourceId": 2,
    "projectId": 2,
    "organizationId": 1,
    "lastUpdatedAt": "2026-03-04T19:13:29.57165",
    "lastUpdatedBy": 1,
    "isArchived": false,
    "fileType": null,
    "tags": [],
    "labels": [],
    "class_name": "Performance Requirement"
  },
  {
    "id": 13,
    "name": "PERF-002: Propulsion Efficiency",
    "description": "Propulsion system shall achieve minimum 8 g/W thrust efficiency",
    "uri": null,
    "properties": {
      "efficiency": "8 g/W",
      "parent_req": "SYS-004"
    },
    "objectStorageId": null,
    "originalId": "PERF-002",
    "classId": 11,
    "dataSourceId": 2,
    "projectId": 2,
    "organizationId": 1,
    "lastUpdatedAt": "2026-03-04T19:13:29.57165",
    "lastUpdatedBy": 1,
    "isArchived": false,
    "fileType": null,
    "tags": [],
    "labels": [],
    "class_name": "Performance Requirement"
  },
  {
    "id": 14,
    "name": "PERF-003: Battery Energy Density",
    "description": "Battery pack shall provide minimum 200 Wh/kg energy density",
    "uri": null,
    "properties": {
      "parent_req": "SYS-004",
      "energy_density": "200 Wh/kg"
    },
    "objectStorageId": null,
    "originalId": "PERF-003",
    "classId": 11,
    "dataSourceId": 2,
    "projectId": 2,
    "organizationId": 1,
    "lastUpdatedAt": "2026-03-04T19:13:29.57165",
    "lastUpdatedBy": 1,
    "isArchived": false,
    "fileType": null,
    "tags": [],
    "labels": [],
    "class_name": "Performance Requirement"
  },
  {
    "id": 15,
    "name": "PERF-004: Drag Coefficient",
    "description": "Airframe Cd shall not exceed 0.028 at cruise",
    "uri": null,
    "properties": {
      "max_cd": 0.028,
      "parent_req": "SYS-003",
      "flight_condition": "cruise"
    },
    "objectStorageId": null,
    "originalId": "PERF-004",
    "classId": 11,
    "dataSourceId": 2,
    "projectId": 2,
    "organizationId": 1,
    "lastUpdatedAt": "2026-03-04T19:13:29.57165",
    "lastUpdatedBy": 1,
    "isArchived": false,
    "fileType": null,
    "tags": [],
    "labels": [],
    "class_name": "Performance Requirement"
  },
  {
    "id": 16,
    "name": "PERF-005: Avionics Power Budget",
    "description": "Total avionics power consumption shall not exceed 45W",
    "uri": null,
    "properties": {
      "max_power": "45 W",
      "parent_req": "SYS-004"
    },
    "objectStorageId": null,
    "originalId": "PERF-005",
    "classId": 11,
    "dataSourceId": 2,
    "projectId": 2,
    "organizationId": 1,
    "lastUpdatedAt": "2026-03-04T19:13:29.57165",
    "lastUpdatedBy": 1,
    "isArchived": false,
    "fileType": null,
    "tags": [],
    "labels": [],
    "class_name": "Performance Requirement"
  },
  {
    "id": 17,
    "name": "PERF-006: GPS Accuracy",
    "description": "Navigation solution shall achieve 2m CEP accuracy",
    "uri": null,
    "properties": {
      "accuracy": "2m CEP",
      "parent_req": "SYS-008"
    },
    "objectStorageId": null,
    "originalId": "PERF-006",
    "classId": 11,
    "dataSourceId": 2,
    "projectId": 2,
    "organizationId": 1,
    "lastUpdatedAt": "2026-03-04T19:13:29.57165",
    "lastUpdatedBy": 1,
    "isArchived": false,
    "fileType": null,
    "tags": [],
    "labels": [],
    "class_name": "Performance Requirement"
  },
  {
    "id": 18,
    "name": "PERF-007: Thermal Envelope",
    "description": "Electronics shall maintain junction temp below 85C across operating range",
    "uri": null,
    "properties": {
      "parent_req": "SYS-005",
      "max_junction_temp": "85 C"
    },
    "objectStorageId": null,
    "originalId": "PERF-007",
    "classId": 11,
    "dataSourceId": 2,
    "projectId": 2,
    "organizationId": 1,
    "lastUpdatedAt": "2026-03-04T19:13:29.57165",
    "lastUpdatedBy": 1,
    "isArchived": false,
    "fileType": null,
    "tags": [],
    "labels": [],
    "class_name": "Performance Requirement"
  }
]